LICENSE.rst
MANIFEST.in
README.rst
setup.py
pyzenfolio/__init__.py
pyzenfolio/api.py
pyzenfolio/constants.py
pyzenfolio/exceptions.py
pyzenfolio/helpers.py
pyzenfolio/utils.py
pyzenfolio/validate.py
pyzenfolio.egg-info/PKG-INFO
pyzenfolio.egg-info/SOURCES.txt
pyzenfolio.egg-info/dependency_links.txt
pyzenfolio.egg-info/requires.txt
pyzenfolio.egg-info/top_level.txt