Metadata-Version: 1.1
Name: pyzenfolio
Version: 0.9
Summary: Light-weight Zenfolio API Python wrapper.
Home-page: https://github.com/miki725/pyzenfolio
Author: Miroslav Shubernetskiy
Author-email: miroslav@miki725.com
License: MIT
Keywords: z,e,n,f,o,l,i,o
Platform: UNKNOWN
Classifier: Development Status :: 3 - Alpha
Classifier: Intended Audience :: Developers
Classifier: Operating System :: OS Independent
Classifier: Programming Language :: Python
Classifier: Topic :: Utilities
Classifier: License :: OSI Approved :: MIT License
Classifier: Topic :: Internet :: WWW/HTTP
Classifier: Programming Language :: Python
